LICENSE
MANIFEST.in
README.md
setup.py
JBioSeqTools.egg-info/PKG-INFO
JBioSeqTools.egg-info/SOURCES.txt
JBioSeqTools.egg-info/dependency_links.txt
JBioSeqTools.egg-info/requires.txt
JBioSeqTools.egg-info/top_level.txt
jbst/__init__.py
jbst/install.py
jbst/seq_tools.py
jbst/vector_build.py
jbst/data/backbone.xlsx
jbst/data/codons.xlsx
jbst/data/enzymes.xlsx
jbst/data/fluorescent_tag.xlsx
jbst/data/linkers.xlsx
jbst/data/polya.xlsx
jbst/data/promoters.xlsx
jbst/data/regulators.xlsx
jbst/data/restriction_enzymes.xlsx
jbst/data/rnai_scoring.xlsx
jbst/data/selectors.xlsx
jbst/data/sh_loops.xlsx
jbst/data/vector_capacity.xlsx
jbst/data/vectors.xlsx
jbst/tests/__init__.py
jbst/tests/fasta_vector_test.fasta
jbst/tests/jseq_tests.py