Metadata-Version: 2.1
Name: JBioSeqTools
Version: 2.0.4
Summary: JBioSeqTools
Author: Jakub Kubis
Author-email: jbiosystem@gmail.com
License: MIT
Keywords: sequence,optimization,vectors,AAV,GC,restriction enzyme
Classifier: Development Status :: 3 - Alpha
Classifier: Programming Language :: Python :: 3
Classifier: Operating System :: MacOS :: MacOS X
Classifier: Operating System :: Microsoft :: Windows
Classifier: Operating System :: POSIX :: Linux
Requires-Python: >=3.8
License-File: LICENSE
